siglent_sds/__init__.py
siglent_sds/base.py
siglent_sds/connectors.py
siglent_sds/devices.py
siglent_sds/examples/__init__.py
siglent_sds/examples/sds_notebook.ipynb
siglent_sds/examples/sds_plot.py
siglent_sds/examples/sds_plot.ui
siglent_sds/examples/sds_repl.py
siglent_sds/utils.py
siglent_sds-0.2.5.dist-info/LICENSE
siglent_sds-0.2.5.dist-info/METADATA
siglent_sds-0.2.5.dist-info/WHEEL
siglent_sds-0.2.5.dist-info/RECORD
