Metadata-Version: 2.1
Name: siglent-sds
Version: 0.2.5
Summary: Interface to the Siglent SDS series of oscilloscopes.
Author: Patrick Tapping
Author-email: mail@patricktapping.com
Requires-Python: >=3.9,<3.13
Classifier: Programming Language :: Python :: 3
Classifier: Programming Language :: Python :: 3.9
Classifier: Programming Language :: Python :: 3.10
Classifier: Programming Language :: Python :: 3.11
Classifier: Programming Language :: Python :: 3.12
Provides-Extra: examples
Requires-Dist: numpy (>=2.0.0,<3.0.0)
Requires-Dist: pyqtgraph (>=0.13.7,<0.14.0) ; extra == "examples"
Requires-Dist: pyside6 (>=6.7.2,<7.0.0) ; extra == "examples"
